{
  "Timestamp": "2015-12-23T06:07:42+00:00",
  "Ack": "SuccessWithWarning",
  "CorrelationID": "2602c38e2df26",
  "Errors": [
    {
      "ShortMessage": "Search warning",
      "LongMessage": "The number of results were truncated. Please change your search parameters if you wish to see all your results.",
      "ErrorCode": "11002",
      "SeverityCode": "Warning"
    }
  ],
  "Version": "98.0",
  "Build": "18308778",
  "PaymentTransactions": [
    {
      "Timestamp": "2015-12-23T06:03:08+00:00",
      "Timezone": "GMT",
      "Type": "Recurring Payment",
      "PayerDisplayName": "Сергей Шустиковы",
      "TransactionID": "I-T7MH95HPBG59",
      "Status": "Created"
    },
    {
      "Timestamp": "2015-12-23T06:00:46+00:00",
      "Timezone": "GMT",
      "Type": "Recurring Payment",
      "PayerDisplayName": "Сергей Шустиковы",
      "TransactionID": "I-SB4T8SEAKER9",
      "Status": "Created"
    },
    {
      "Timestamp": "2015-12-23T05:57:25+00:00",
      "Timezone": "GMT",
      "Type": "Recurring Payment",
      "PayerDisplayName": "Сергей Шустиковы",
      "TransactionID": "I-MYR0XB2XT5KX",
      "Status": "Created"
    },
    {
      "Timestamp": "2015-12-23T05:54:51+00:00",
      "Timezone": "GMT",
      "Type": "Recurring Payment",
      "PayerDisplayName": "Сергей Шустиковы",
      "TransactionID": "I-R3HMC6DTFWDR",
      "Status": "Created"
    },
    {
      "Timestamp": "2015-12-23T05:52:13+00:00",
      "Timezone": "GMT",
      "Type": "Recurring Payment",
      "PayerDisplayName": "Сергей Шустиковы",
      "TransactionID": "I-5KLKJ301YRKW",
      "Status": "Created"
    },
    {
      "Timestamp": "2015-12-23T05:50:49+00:00",
      "Timezone": "GMT",
      "Type": "Recurring Payment",
      "PayerDisplayName": "Сергей Шустиковы",
      "TransactionID": "I-KK1WU2L9KA2H",
      "Status": "Created"
    },
    {
      "Timestamp": "2015-12-23T05:49:31+00:00",
      "Timezone": "GMT",
      "Type": "Payment",
      "PayerDisplayName": "Jon Doe",
      "TransactionID": "1EC59434FD7755331",
      "Status": "Completed",
      "GrossAmount": {
        "currencyID": "USD",
        "value": "1.00"
      },
      "FeeAmount": {
        "currencyID": "USD",
        "value": "-0.33"
      },
      "NetAmount": {
        "currencyID": "USD",
        "value": "0.67"
      }
    },
    {
      "Timestamp": "2015-12-23T05:41:57+00:00",
      "Timezone": "GMT",
      "Type": "Recurring Payment",
      "PayerDisplayName": "Сергей Шустиковы",
      "TransactionID": "I-0N4NH5KPFLLG",
      "Status": "Created"
    },
    {
      "Timestamp": "2015-12-23T05:40:01+00:00",
      "Timezone": "GMT",
      "Type": "Recurring Payment",
      "PayerDisplayName": "Сергей Шустиковы",
      "TransactionID": "I-7D1X1XK3RMD0",
      "Status": "Created"
    },
    {
      "Timestamp": "2015-12-23T05:39:03+00:00",
      "Timezone": "GMT",
      "Type": "Recurring Payment",
      "PayerDisplayName": "Сергей Шустиковы",
      "TransactionID": "I-7AVPW16HSCP5",
      "Status": "Created"
    },
    {
      "Timestamp": "2015-12-23T05:19:30+00:00",
      "Timezone": "GMT",
      "Type": "Recurring Payment",
      "PayerDisplayName": "test buyer",
      "TransactionID": "I-MNA8MS84DEWU",
      "Status": "Created"
    },
    {
      "Timestamp": "2015-12-23T05:14:24+00:00",
      "Timezone": "GMT",
      "Type": "Recurring Payment",
      "PayerDisplayName": "test buyer",
      "TransactionID": "I-XLJJEKJWXG7M",
      "Status": "Created"
    },
    {
      "Timestamp": "2015-12-23T05:10:20+00:00",
      "Timezone": "GMT",
      "Type": "Authorization",
      "PayerDisplayName": "supratim mukherjee",
      "TransactionID": "2FD30441UC5738128",
      "Status": "Pending",
      "GrossAmount": {
        "currencyID": "AUD",
        "value": "50.00"
      },
      "FeeAmount": {
        "currencyID": "AUD",
        "value": "0.00"
      },
      "NetAmount": {
        "currencyID": "AUD",
        "value": "50.00"
      }
    },
    {
      "Timestamp": "2015-12-23T02:01:35+00:00",
      "Timezone": "GMT",
      "Type": "Payment",
      "Payer": "tien-yi.chi-buyer@logicsolutions.com",
      "PayerDisplayName": "test buyer",
      "TransactionID": "1NM48995CA1303609",
      "Status": "Completed",
      "GrossAmount": {
        "currencyID": "USD",
        "value": "400.00"
      },
      "FeeAmount": {
        "currencyID": "USD",
        "value": "-11.90"
      },
      "NetAmount": {
        "currencyID": "USD",
        "value": "388.10"
      }
    },
    {
      "Timestamp": "2015-12-23T01:55:51+00:00",
      "Timezone": "GMT",
      "Type": "Payment",
      "Payer": "tien-yi.chi-buyer@logicsolutions.com",
      "PayerDisplayName": "test buyer",
      "TransactionID": "1WD17606NS930292M",
      "Status": "Completed",
      "GrossAmount": {
        "currencyID": "USD",
        "value": "500.00"
      },
      "FeeAmount": {
        "currencyID": "USD",
        "value": "-14.80"
      },
      "NetAmount": {
        "currencyID": "USD",
        "value": "485.20"
      }
    },
    {
      "Timestamp": "2015-12-23T01:53:18+00:00",
      "Timezone": "GMT",
      "Type": "Payment",
      "Payer": "tien-yi.chi-buyer@logicsolutions.com",
      "PayerDisplayName": "test buyer",
      "TransactionID": "66865758PF4957708",
      "Status": "Completed",
      "GrossAmount": {
        "currencyID": "USD",
        "value": "750.00"
      },
      "FeeAmount": {
        "currencyID": "USD",
        "value": "-22.05"
      },
      "NetAmount": {
        "currencyID": "USD",
        "value": "727.95"
      }
    },
    {
      "Timestamp": "2015-12-23T00:50:28+00:00",
      "Timezone": "GMT",
      "Type": "Payment",
      "Payer": "buyer-paypal@mexfun.com",
      "PayerDisplayName": "Evelio Mis",
      "TransactionID": "57563230NW4046300",
      "Status": "Completed",
      "GrossAmount": {
        "currencyID": "USD",
        "value": "1.00"
      },
      "FeeAmount": {
        "currencyID": "USD",
        "value": "-0.34"
      },
      "NetAmount": {
        "currencyID": "USD",
        "value": "0.66"
      }
    },
    {
      "Timestamp": "2015-12-23T00:32:11+00:00",
      "Timezone": "GMT",
      "Type": "Recurring Payment",
      "PayerDisplayName": "test buyer",
      "TransactionID": "I-M9R857PH53L6",
      "Status": "Canceled"
    },
    {
      "Timestamp": "2015-12-23T00:13:24+00:00",
      "Timezone": "GMT",
      "Type": "Order",
      "Payer": "Buyer@sciencecomputing.com",
      "PayerDisplayName": "Buyer Test",
      "TransactionID": "O-73F377224M7248548",
      "Status": "Pending",
      "GrossAmount": {
        "currencyID": "USD",
        "value": "244.00"
      },
      "FeeAmount": {
        "currencyID": "USD",
        "value": "0.00"
      },
      "NetAmount": {
        "currencyID": "USD",
        "value": "244.00"
      }
    },
    {
      "Timestamp": "2015-12-22T23:05:38+00:00",
      "Timezone": "GMT",
      "Type": "Order",
      "Payer": "Buyer@sciencecomputing.com",
      "PayerDisplayName": "Buyer Test",
      "TransactionID": "O-0D588300ME5641207",
      "Status": "Pending",
      "GrossAmount": {
        "currencyID": "USD",
        "value": "366.00"
      },
      "FeeAmount": {
        "currencyID": "USD",
        "value": "0.00"
      },
      "NetAmount": {
        "currencyID": "USD",
        "value": "366.00"
      }
    },
    {
      "Timestamp": "2015-12-22T22:08:47+00:00",
      "Timezone": "GMT",
      "Type": "Payment",
      "Payer": "fonkydud@gmail.com",
      "PayerDisplayName": "Julien Krier's Test Store",
      "TransactionID": "7C515175WW219033J",
      "Status": "Completed",
      "GrossAmount": {
        "currencyID": "USD",
        "value": "1.00"
      },
      "FeeAmount": {
        "currencyID": "USD",
        "value": "-0.34"
      },
      "NetAmount": {
        "currencyID": "USD",
        "value": "0.66"
      }
    },
    {
      "Timestamp": "2015-12-22T19:49:00+00:00",
      "Timezone": "GMT",
      "Type": "Recurring Payment",
      "Payer": "neozilus-facilitator@gmail.com",
      "PayerDisplayName": "facilitator account's Test Store",
      "TransactionID": "61C88212RV384804S",
      "Status": "Completed",
      "GrossAmount": {
        "currencyID": "USD",
        "value": "1.00"
      },
      "FeeAmount": {
        "currencyID": "USD",
        "value": "-0.33"
      },
      "NetAmount": {
        "currencyID": "USD",
        "value": "0.67"
      }
    },
    {
      "Timestamp": "2015-12-22T19:48:45+00:00",
      "Timezone": "GMT",
      "Type": "Recurring Payment",
      "PayerDisplayName": "facilitator account's Test Store",
      "TransactionID": "I-VL50C76YNB6S",
      "Status": "Created"
    },
    {
      "Timestamp": "2015-12-22T17:59:09+00:00",
      "Timezone": "GMT",
      "Type": "Payment",
      "Payer": "henry.peng-buyer@logicsolutions.com",
      "PayerDisplayName": "test buyer",
      "TransactionID": "2CM72920DC4823200",
      "Status": "Completed",
      "GrossAmount": {
        "currencyID": "USD",
        "value": "750.00"
      },
      "FeeAmount": {
        "currencyID": "USD",
        "value": "-22.05"
      },
      "NetAmount": {
        "currencyID": "USD",
        "value": "727.95"
      }
    },
    {
      "Timestamp": "2015-12-22T17:54:40+00:00",
      "Timezone": "GMT",
      "Type": "Order",
      "Payer": "customer-acc@easypaymentgateway.com",
      "PayerDisplayName": "Ruben Fernandez Pena",
      "TransactionID": "O-6D16775102061070T",
      "Status": "Pending",
      "GrossAmount": {
        "currencyID": "USD",
        "value": "10.54"
      },
      "FeeAmount": {
        "currencyID": "USD",
        "value": "0.00"
      },
      "NetAmount": {
        "currencyID": "USD",
        "value": "10.54"
      }
    },
    {
      "Timestamp": "2015-12-22T16:57:37+00:00",
      "Timezone": "GMT",
      "Type": "Payment",
      "Payer": "customer-acc@easypaymentgateway.com",
      "PayerDisplayName": "Ruben Fernandez Pena",
      "TransactionID": "8JP427320C907630G",
      "Status": "Completed",
      "GrossAmount": {
        "currencyID": "USD",
        "value": "1.00"
      },
      "FeeAmount": {
        "currencyID": "USD",
        "value": "-0.34"
      },
      "NetAmount": {
        "currencyID": "USD",
        "value": "0.66"
      }
    },
    {
      "Timestamp": "2015-12-22T16:56:06+00:00",
      "Timezone": "GMT",
      "Type": "Authorization",
      "Payer": "customer-acc@easypaymentgateway.com",
      "PayerDisplayName": "Ruben Fernandez Pena",
      "TransactionID": "3R85284237547934W",
      "Status": "Voided",
      "GrossAmount": {
        "currencyID": "USD",
        "value": "1.00"
      },
      "FeeAmount": {
        "currencyID": "USD",
        "value": "0.00"
      },
      "NetAmount": {
        "currencyID": "USD",
        "value": "1.00"
      }
    },
    {
      "Timestamp": "2015-12-22T16:55:20+00:00",
      "Timezone": "GMT",
      "Type": "Order",
      "Payer": "customer-acc@easypaymentgateway.com",
      "PayerDisplayName": "Ruben Fernandez Pena",
      "TransactionID": "O-2TM68574VU8540530",
      "Status": "Completed",
      "GrossAmount": {
        "currencyID": "USD",
        "value": "10.54"
      },
      "FeeAmount": {
        "currencyID": "USD",
        "value": "0.00"
      },
      "NetAmount": {
        "currencyID": "USD",
        "value": "10.54"
      }
    },
    {
      "Timestamp": "2015-12-22T16:50:39+00:00",
      "Timezone": "GMT",
      "Type": "Payment",
      "PayerDisplayName": "John Doe",
      "TransactionID": "2H8134580W270510X",
      "Status": "Completed",
      "GrossAmount": {
        "currencyID": "USD",
        "value": "1.00"
      },
      "FeeAmount": {
        "currencyID": "USD",
        "value": "-0.33"
      },
      "NetAmount": {
        "currencyID": "USD",
        "value": "0.67"
      }
    },
    {
      "Timestamp": "2015-12-22T15:16:07+00:00",
      "Timezone": "GMT",
      "Type": "Recurring Payment",
      "Payer": "info-buyer@officinedigitali.ch",
      "PayerDisplayName": "test buyer",
      "TransactionID": "6H404583V5427263U",
      "Status": "Completed",
      "GrossAmount": {
        "currencyID": "USD",
        "value": "1.00"
      },
      "FeeAmount": {
        "currencyID": "USD",
        "value": "-0.34"
      },
      "NetAmount": {
        "currencyID": "USD",
        "value": "0.66"
      }
    },
    {
      "Timestamp": "2015-12-22T15:15:56+00:00",
      "Timezone": "GMT",
      "Type": "Recurring Payment",
      "PayerDisplayName": "test buyer",
      "TransactionID": "I-WTSBNYNJYU7M",
      "Status": "Created"
    },
    {
      "Timestamp": "2015-12-22T15:11:07+00:00",
      "Timezone": "GMT",
      "Type": "Recurring Payment",
      "Payer": "hai@panda-os.com",
      "PayerDisplayName": "hai levi",
      "TransactionID": "0KA71519WT8067348",
      "Status": "Completed",
      "GrossAmount": {
        "currencyID": "USD",
        "value": "1.00"
      },
      "FeeAmount": {
        "currencyID": "USD",
        "value": "-0.33"
      },
      "NetAmount": {
        "currencyID": "USD",
        "value": "0.67"
      }
    },
    {
      "Timestamp": "2015-12-22T15:10:50+00:00",
      "Timezone": "GMT",
      "Type": "Recurring Payment",
      "PayerDisplayName": "hai levi",
      "TransactionID": "I-VRC0GUAUD87A",
      "Status": "Created"
    },
    {
      "Timestamp": "2015-12-22T14:00:39+00:00",
      "Timezone": "GMT",
      "Type": "Payment",
      "Payer": "enduser_biz@gmail.com",
      "PayerDisplayName": "Damien Steiger",
      "TransactionID": "1BD63515FD3098844",
      "Status": "Completed",
      "GrossAmount": {
        "currencyID": "USD",
        "value": "4.00"
      },
      "FeeAmount": {
        "currencyID": "USD",
        "value": "-0.42"
      },
      "NetAmount": {
        "currencyID": "USD",
        "value": "3.58"
      }
    },
    {
      "Timestamp": "2015-12-22T13:56:47+00:00",
      "Timezone": "GMT",
      "Type": "Payment",
      "Payer": "enduser_biz@gmail.com",
      "PayerDisplayName": "Damien Steiger",
      "TransactionID": "1MH03501D4719083S",
      "Status": "Completed",
      "GrossAmount": {
        "currencyID": "USD",
        "value": "4.00"
      },
      "FeeAmount": {
        "currencyID": "USD",
        "value": "-0.42"
      },
      "NetAmount": {
        "currencyID": "USD",
        "value": "3.58"
      }
    },
    {
      "Timestamp": "2015-12-22T13:54:00+00:00",
      "Timezone": "GMT",
      "Type": "Unclaimed Funds Returned",
      "PayerDisplayName": "Mass Payment",
      "TransactionID": "8X841810849356311",
      "Status": "Completed",
      "GrossAmount": {
        "currencyID": "USD",
        "value": "3.00"
      },
      "FeeAmount": {
        "currencyID": "USD",
        "value": "0.00"
      },
      "NetAmount": {
        "currencyID": "USD",
        "value": "3.00"
      }
    },
    {
      "Timestamp": "2015-12-22T13:51:01+00:00",
      "Timezone": "GMT",
      "Type": "Unclaimed Funds Returned",
      "PayerDisplayName": "Mass Payment",
      "TransactionID": "36739661MU045352F",
      "Status": "Completed",
      "GrossAmount": {
        "currencyID": "USD",
        "value": "3.00"
      },
      "FeeAmount": {
        "currencyID": "USD",
        "value": "0.00"
      },
      "NetAmount": {
        "currencyID": "USD",
        "value": "3.00"
      }
    },
    {
      "Timestamp": "2015-12-22T13:51:00+00:00",
      "Timezone": "GMT",
      "Type": "Unclaimed Funds Returned",
      "PayerDisplayName": "Mass Payment",
      "TransactionID": "30U88205GG0297146",
      "Status": "Completed",
      "GrossAmount": {
        "currencyID": "USD",
        "value": "3.00"
      },
      "FeeAmount": {
        "currencyID": "USD",
        "value": "0.00"
      },
      "NetAmount": {
        "currencyID": "USD",
        "value": "3.00"
      }
    },
    {
      "Timestamp": "2015-12-22T13:46:00+00:00",
      "Timezone": "GMT",
      "Type": "Unclaimed Funds Returned",
      "PayerDisplayName": "Mass Payment",
      "TransactionID": "3DP12386PN631724C",
      "Status": "Completed",
      "GrossAmount": {
        "currencyID": "USD",
        "value": "3.00"
      },
      "FeeAmount": {
        "currencyID": "USD",
        "value": "0.00"
      },
      "NetAmount": {
        "currencyID": "USD",
        "value": "3.00"
      }
    },
    {
      "Timestamp": "2015-12-22T13:45:01+00:00",
      "Timezone": "GMT",
      "Type": "Unclaimed Funds Returned",
      "PayerDisplayName": "Mass Payment",
      "TransactionID": "6FN96807A3906930Y",
      "Status": "Completed",
      "GrossAmount": {
        "currencyID": "USD",
        "value": "3.00"
      },
      "FeeAmount": {
        "currencyID": "USD",
        "value": "0.00"
      },
      "NetAmount": {
        "currencyID": "USD",
        "value": "3.00"
      }
    },
    {
      "Timestamp": "2015-12-22T13:45:00+00:00",
      "Timezone": "GMT",
      "Type": "Unclaimed Funds Returned",
      "PayerDisplayName": "Mass Payment",
      "TransactionID": "5MB98676LS8037637",
      "Status": "Completed",
      "GrossAmount": {
        "currencyID": "USD",
        "value": "3.00"
      },
      "FeeAmount": {
        "currencyID": "USD",
        "value": "0.00"
      },
      "NetAmount": {
        "currencyID": "USD",
        "value": "3.00"
      }
    },
    {
      "Timestamp": "2015-12-22T13:45:00+00:00",
      "Timezone": "GMT",
      "Type": "Unclaimed Funds Returned",
      "PayerDisplayName": "Mass Payment",
      "TransactionID": "8CR90741JJ959671F",
      "Status": "Completed",
      "GrossAmount": {
        "currencyID": "USD",
        "value": "3.00"
      },
      "FeeAmount": {
        "currencyID": "USD",
        "value": "0.00"
      },
      "NetAmount": {
        "currencyID": "USD",
        "value": "3.00"
      }
    },
    {
      "Timestamp": "2015-12-22T13:24:25+00:00",
      "Timezone": "GMT",
      "Type": "Payment",
      "Payer": "tahir._1199964278_per@gmail.com",
      "PayerDisplayName": "Test User",
      "TransactionID": "2L4463438H594211R",
      "Status": "Completed",
      "GrossAmount": {
        "currencyID": "USD",
        "value": "1.00"
      },
      "FeeAmount": {
        "currencyID": "USD",
        "value": "-0.33"
      },
      "NetAmount": {
        "currencyID": "USD",
        "value": "0.67"
      }
    },
    {
      "Timestamp": "2015-12-22T12:55:12+00:00",
      "Timezone": "GMT",
      "Type": "Payment",
      "Payer": "myemail@mydomain.com",
      "PayerDisplayName": "Frank Enstien",
      "TransactionID": "3NK39177FN136461S",
      "Status": "Completed",
      "GrossAmount": {
        "currencyID": "USD",
        "value": "10.00"
      },
      "FeeAmount": {
        "currencyID": "USD",
        "value": "-0.59"
      },
      "NetAmount": {
        "currencyID": "USD",
        "value": "9.41"
      }
    },
    {
      "Timestamp": "2015-12-22T12:46:57+00:00",
      "Timezone": "GMT",
      "Type": "Payment",
      "Payer": "sachin_thombare91@yahoo.com",
      "PayerDisplayName": "Halima Koundi",
      "TransactionID": "9F420257P9566671P",
      "Status": "Completed",
      "GrossAmount": {
        "currencyID": "USD",
        "value": "197.00"
      },
      "FeeAmount": {
        "currencyID": "USD",
        "value": "-6.01"
      },
      "NetAmount": {
        "currencyID": "USD",
        "value": "190.99"
      }
    },
    {
      "Timestamp": "2015-12-22T12:44:20+00:00",
      "Timezone": "GMT",
      "Type": "Payment",
      "Payer": "sachin_thombare91@yahoo.com",
      "PayerDisplayName": "Aneesh Kansal Testerson",
      "TransactionID": "50X95142XS7917537",
      "Status": "Completed",
      "GrossAmount": {
        "currencyID": "USD",
        "value": "3.00"
      },
      "FeeAmount": {
        "currencyID": "USD",
        "value": "-0.39"
      },
      "NetAmount": {
        "currencyID": "USD",
        "value": "2.61"
      }
    },
    {
      "Timestamp": "2015-12-22T11:30:15+00:00",
      "Timezone": "GMT",
      "Type": "Temporary Hold",
      "PayerDisplayName": "PayPal",
      "TransactionID": "9973473789530244Y",
      "Status": "Placed",
      "GrossAmount": {
        "currencyID": "USD",
        "value": "-3.06"
      },
      "FeeAmount": {
        "currencyID": "USD",
        "value": "0.00"
      },
      "NetAmount": {
        "currencyID": "USD",
        "value": "-3.06"
      }
    },
    {
      "Timestamp": "2015-12-22T11:30:15+00:00",
      "Timezone": "GMT",
      "Type": "Mass Payment Sent",
      "PayerDisplayName": "Mass Payment",
      "TransactionID": "1E105880ND2446732",
      "Status": "Processed",
      "GrossAmount": {
        "currencyID": "USD",
        "value": "-3.00"
      },
      "FeeAmount": {
        "currencyID": "USD",
        "value": "-0.06"
      },
      "NetAmount": {
        "currencyID": "USD",
        "value": "-3.06"
      }
    },
    {
      "Timestamp": "2015-12-22T11:29:31+00:00",
      "Timezone": "GMT",
      "Type": "Recurring Payment",
      "Payer": "tahir._1199964278_per@gmail.com",
      "PayerDisplayName": "Test User",
      "TransactionID": "76F56180X6370851L",
      "Status": "Completed",
      "GrossAmount": {
        "currencyID": "USD",
        "value": "1.00"
      },
      "FeeAmount": {
        "currencyID": "USD",
        "value": "-0.33"
      },
      "NetAmount": {
        "currencyID": "USD",
        "value": "0.67"
      }
    },
    {
      "Timestamp": "2015-12-22T11:29:28+00:00",
      "Timezone": "GMT",
      "Type": "Recurring Payment",
      "Payer": "aisha-buyer@gmail.com",
      "PayerDisplayName": "Aisha Chopra",
      "TransactionID": "4VJ34075J4908670H",
      "Status": "Completed",
      "GrossAmount": {
        "currencyID": "USD",
        "value": "1.00"
      },
      "FeeAmount": {
        "currencyID": "USD",
        "value": "-0.33"
      },
      "NetAmount": {
        "currencyID": "USD",
        "value": "0.67"
      }
    },
    {
      "Timestamp": "2015-12-22T11:28:58+00:00",
      "Timezone": "GMT",
      "Type": "Recurring Payment",
      "Payer": "w-frost@yandex.ru",
      "PayerDisplayName": "Home",
      "TransactionID": "60A6959735776394G",
      "Status": "Completed",
      "GrossAmount": {
        "currencyID": "USD",
        "value": "0.02"
      },
      "FeeAmount": {
        "currencyID": "USD",
        "value": "-0.02"
      },
      "NetAmount": {
        "currencyID": "USD",
        "value": "0.00"
      }
    },
    {
      "Timestamp": "2015-12-22T11:28:55+00:00",
      "Timezone": "GMT",
      "Type": "Recurring Payment",
      "Payer": "cabbondanza-buyer@cmd.com.ar",
      "PayerDisplayName": "test buyer",
      "TransactionID": "96664850PJ3464719",
      "Status": "Completed",
      "GrossAmount": {
        "currencyID": "USD",
        "value": "10.00"
      },
      "FeeAmount": {
        "currencyID": "USD",
        "value": "-0.59"
      },
      "NetAmount": {
        "currencyID": "USD",
        "value": "9.41"
      }
    },
    {
      "Timestamp": "2015-12-22T11:28:52+00:00",
      "Timezone": "GMT",
      "Type": "Recurring Payment",
      "Payer": "w-frost@yandex.ru",
      "PayerDisplayName": "Home",
      "TransactionID": "68Y01191357123409",
      "Status": "Completed",
      "GrossAmount": {
        "currencyID": "USD",
        "value": "0.02"
      },
      "FeeAmount": {
        "currencyID": "USD",
        "value": "-0.02"
      },
      "NetAmount": {
        "currencyID": "USD",
        "value": "0.00"
      }
    },
    {
      "Timestamp": "2015-12-22T11:28:48+00:00",
      "Timezone": "GMT",
      "Type": "Recurring Payment",
      "Payer": "w-frost@yandex.ru",
      "PayerDisplayName": "Home",
      "TransactionID": "93P211707Y1971207",
      "Status": "Completed",
      "GrossAmount": {
        "currencyID": "USD",
        "value": "0.04"
      },
      "FeeAmount": {
        "currencyID": "USD",
        "value": "-0.04"
      },
      "NetAmount": {
        "currencyID": "USD",
        "value": "0.00"
      }
    },
    {
      "Timestamp": "2015-12-22T11:28:45+00:00",
      "Timezone": "GMT",
      "Type": "Recurring Payment",
      "Payer": "miharu@internetnextstep.com",
      "PayerDisplayName": "Miharu Fischer",
      "TransactionID": "7M447460JM246194L",
      "Status": "Completed",
      "GrossAmount": {
        "currencyID": "USD",
        "value": "13.27"
      },
      "FeeAmount": {
        "currencyID": "USD",
        "value": "-0.82"
      },
      "NetAmount": {
        "currencyID": "USD",
        "value": "12.45"
      }
    },
    {
      "Timestamp": "2015-12-22T11:28:41+00:00",
      "Timezone": "GMT",
      "Type": "Recurring Payment",
      "Payer": "buyerdemo@esferasoft.com",
      "PayerDisplayName": "buyer test",
      "TransactionID": "5YT23978BA816250L",
      "Status": "Completed",
      "GrossAmount": {
        "currencyID": "USD",
        "value": "7.00"
      },
      "FeeAmount": {
        "currencyID": "USD",
        "value": "-0.50"
      },
      "NetAmount": {
        "currencyID": "USD",
        "value": "6.50"
      }
    },
    {
      "Timestamp": "2015-12-22T11:28:37+00:00",
      "Timezone": "GMT",
      "Type": "Recurring Payment",
      "Payer": "yahoosoo80@gmail.com",
      "PayerDisplayName": "Test yaoo soo",
      "TransactionID": "50T78278DC374115X",
      "Status": "Completed",
      "GrossAmount": {
        "currencyID": "USD",
        "value": "1.00"
      },
      "FeeAmount": {
        "currencyID": "USD",
        "value": "-0.33"
      },
      "NetAmount": {
        "currencyID": "USD",
        "value": "0.67"
      }
    },
    {
      "Timestamp": "2015-12-22T11:28:33+00:00",
      "Timezone": "GMT",
      "Type": "Recurring Payment",
      "Payer": "cruzazul_magistroni@hotmail.com",
      "PayerDisplayName": "Uriel Hernandez",
      "TransactionID": "90W61921F72204811",
      "Status": "Completed",
      "GrossAmount": {
        "currencyID": "USD",
        "value": "1.00"
      },
      "FeeAmount": {
        "currencyID": "USD",
        "value": "-0.33"
      },
      "NetAmount": {
        "currencyID": "USD",
        "value": "0.67"
      }
    },
    {
      "Timestamp": "2015-12-22T11:28:30+00:00",
      "Timezone": "GMT",
      "Type": "Recurring Payment",
      "Payer": "cabbondanza-buyer@cmd.com.ar",
      "PayerDisplayName": "test buyer",
      "TransactionID": "0R561797XA4436226",
      "Status": "Completed",
      "GrossAmount": {
        "currencyID": "USD",
        "value": "10.00"
      },
      "FeeAmount": {
        "currencyID": "USD",
        "value": "-0.59"
      },
      "NetAmount": {
        "currencyID": "USD",
        "value": "9.41"
      }
    },
    {
      "Timestamp": "2015-12-22T11:28:26+00:00",
      "Timezone": "GMT",
      "Type": "Recurring Payment",
      "Payer": "hermione@hogwarts.com",
      "PayerDisplayName": "Hermione Granger",
      "TransactionID": "5C449025Y6159535F",
      "Status": "Completed",
      "GrossAmount": {
        "currencyID": "USD",
        "value": "8.00"
      },
      "FeeAmount": {
        "currencyID": "USD",
        "value": "-0.53"
      },
      "NetAmount": {
        "currencyID": "USD",
        "value": "7.47"
      }
    },
    {
      "Timestamp": "2015-12-22T11:28:23+00:00",
      "Timezone": "GMT",
      "Type": "Recurring Payment",
      "Payer": "pnotari-buyer@cmd.com.ar",
      "PayerDisplayName": "test buyer",
      "TransactionID": "4HT73265XC1409116",
      "Status": "Completed",
      "GrossAmount": {
        "currencyID": "USD",
        "value": "10.00"
      },
      "FeeAmount": {
        "currencyID": "USD",
        "value": "-0.59"
      },
      "NetAmount": {
        "currencyID": "USD",
        "value": "9.41"
      }
    },
    {
      "Timestamp": "2015-12-22T11:28:19+00:00",
      "Timezone": "GMT",
      "Type": "Recurring Payment",
      "Payer": "aisha-buyer@gmail.com",
      "PayerDisplayName": "Aisha Chopra",
      "TransactionID": "9MX18156E5986531F",
      "Status": "Completed",
      "GrossAmount": {
        "currencyID": "USD",
        "value": "1.00"
      },
      "FeeAmount": {
        "currencyID": "USD",
        "value": "-0.33"
      },
      "NetAmount": {
        "currencyID": "USD",
        "value": "0.67"
      }
    },
    {
      "Timestamp": "2015-12-22T11:17:53+00:00",
      "Timezone": "GMT",
      "Type": "Payment",
      "Payer": "customer-acc@easypaymentgateway.com",
      "PayerDisplayName": "Ruben Fernandez Pena",
      "TransactionID": "2TK260102B9716224",
      "Status": "Completed",
      "GrossAmount": {
        "currencyID": "USD",
        "value": "1.00"
      },
      "FeeAmount": {
        "currencyID": "USD",
        "value": "-0.34"
      },
      "NetAmount": {
        "currencyID": "USD",
        "value": "0.66"
      }
    },
    {
      "Timestamp": "2015-12-22T11:17:12+00:00",
      "Timezone": "GMT",
      "Type": "Authorization",
      "Payer": "customer-acc@easypaymentgateway.com",
      "PayerDisplayName": "Ruben Fernandez Pena",
      "TransactionID": "7CF11970RM6530118",
      "Status": "Completed",
      "GrossAmount": {
        "currencyID": "USD",
        "value": "10.54"
      },
      "FeeAmount": {
        "currencyID": "USD",
        "value": "0.00"
      },
      "NetAmount": {
        "currencyID": "USD",
        "value": "10.54"
      }
    },
    {
      "Timestamp": "2015-12-22T11:15:08+00:00",
      "Timezone": "GMT",
      "Type": "Payment",
      "Payer": "customer-acc@easypaymentgateway.com",
      "PayerDisplayName": "Ruben Fernandez Pena",
      "TransactionID": "4JR97126957941241",
      "Status": "Completed",
      "GrossAmount": {
        "currencyID": "USD",
        "value": "10.54"
      },
      "FeeAmount": {
        "currencyID": "USD",
        "value": "-0.71"
      },
      "NetAmount": {
        "currencyID": "USD",
        "value": "9.83"
      }
    },
    {
      "Timestamp": "2015-12-22T11:09:28+00:00",
      "Timezone": "GMT",
      "Type": "Payment",
      "Payer": "customer-acc@easypaymentgateway.com",
      "PayerDisplayName": "Ruben Fernandez Pena",
      "TransactionID": "1LS63904AN786943A",
      "Status": "Completed",
      "GrossAmount": {
        "currencyID": "USD",
        "value": "10.54"
      },
      "FeeAmount": {
        "currencyID": "USD",
        "value": "-0.71"
      },
      "NetAmount": {
        "currencyID": "USD",
        "value": "9.83"
      }
    },
    {
      "Timestamp": "2015-12-22T11:00:59+00:00",
      "Timezone": "GMT",
      "Type": "Payment",
      "Payer": "anton@list.ru",
      "PayerDisplayName": "John Smith",
      "TransactionID": "756249271U5670255",
      "Status": "Completed",
      "GrossAmount": {
        "currencyID": "USD",
        "value": "158.95"
      },
      "FeeAmount": {
        "currencyID": "USD",
        "value": "-4.91"
      },
      "NetAmount": {
        "currencyID": "USD",
        "value": "154.04"
      }
    },
    {
      "Timestamp": "2015-12-22T10:42:57+00:00",
      "Timezone": "GMT",
      "Type": "Payment",
      "Payer": "anton@list.ru",
      "PayerDisplayName": "John Smith",
      "TransactionID": "7DG000858C140992H",
      "Status": "Completed",
      "GrossAmount": {
        "currencyID": "USD",
        "value": "158.95"
      },
      "FeeAmount": {
        "currencyID": "USD",
        "value": "-4.91"
      },
      "NetAmount": {
        "currencyID": "USD",
        "value": "154.04"
      }
    },
    {
      "Timestamp": "2015-12-22T10:34:36+00:00",
      "Timezone": "GMT",
      "Type": "Recurring Payment",
      "PayerDisplayName": "Test User",
      "TransactionID": "I-KESGKLUFK7S6",
      "Status": "Created"
    },
    {
      "Timestamp": "2015-12-22T10:18:37+00:00",
      "Timezone": "GMT",
      "Type": "Payment",
      "Payer": "enduser_biz@gmail.com",
      "PayerDisplayName": "Damien Steiger",
      "TransactionID": "4711938977884793P",
      "Status": "Completed",
      "GrossAmount": {
        "currencyID": "USD",
        "value": "4.00"
      },
      "FeeAmount": {
        "currencyID": "USD",
        "value": "-0.42"
      },
      "NetAmount": {
        "currencyID": "USD",
        "value": "3.58"
      }
    },
    {
      "Timestamp": "2015-12-22T10:12:15+00:00",
      "Timezone": "GMT",
      "Type": "Payment",
      "Payer": "anton@list.ru",
      "PayerDisplayName": "John Smith",
      "TransactionID": "2ML628820K066081H",
      "Status": "Completed",
      "GrossAmount": {
        "currencyID": "USD",
        "value": "98.95"
      },
      "FeeAmount": {
        "currencyID": "USD",
        "value": "-3.17"
      },
      "NetAmount": {
        "currencyID": "USD",
        "value": "95.78"
      }
    },
    {
      "Timestamp": "2015-12-22T10:08:07+00:00",
      "Timezone": "GMT",
      "Type": "Payment",
      "Payer": "dminkin@ya.ru",
      "PayerDisplayName": "dmitry minkin",
      "TransactionID": "4FU59400SU918124T",
      "Status": "Completed",
      "GrossAmount": {
        "currencyID": "USD",
        "value": "104.29"
      },
      "FeeAmount": {
        "currencyID": "USD",
        "value": "-3.32"
      },
      "NetAmount": {
        "currencyID": "USD",
        "value": "100.97"
      }
    },
    {
      "Timestamp": "2015-12-22T10:08:01+00:00",
      "Timezone": "GMT",
      "Type": "Payment",
      "Payer": "anton@list.ru",
      "PayerDisplayName": "John Smith",
      "TransactionID": "0ET60411H4753772T",
      "Status": "Completed",
      "GrossAmount": {
        "currencyID": "USD",
        "value": "98.95"
      },
      "FeeAmount": {
        "currencyID": "USD",
        "value": "-3.17"
      },
      "NetAmount": {
        "currencyID": "USD",
        "value": "95.78"
      }
    },
    {
      "Timestamp": "2015-12-22T10:07:59+00:00",
      "Timezone": "GMT",
      "Type": "Recurring Payment",
      "Payer": "cruzazul_magistroni@hotmail.com",
      "PayerDisplayName": "Uriel Hernandez",
      "TransactionID": "3BJ68914D0243140J",
      "Status": "Completed",
      "GrossAmount": {
        "currencyID": "USD",
        "value": "9.00"
      },
      "FeeAmount": {
        "currencyID": "USD",
        "value": "-0.56"
      },
      "NetAmount": {
        "currencyID": "USD",
        "value": "8.44"
      }
    },
    {
      "Timestamp": "2015-12-22T10:07:55+00:00",
      "Timezone": "GMT",
      "Type": "Recurring Payment",
      "Payer": "cruzazul_magistroni@hotmail.com",
      "PayerDisplayName": "Uriel Hernandez",
      "TransactionID": "7MN72935PT198733H",
      "Status": "Completed",
      "GrossAmount": {
        "currencyID": "USD",
        "value": "9.00"
      },
      "FeeAmount": {
        "currencyID": "USD",
        "value": "-0.56"
      },
      "NetAmount": {
        "currencyID": "USD",
        "value": "8.44"
      }
    },
    {
      "Timestamp": "2015-12-22T10:07:52+00:00",
      "Timezone": "GMT",
      "Type": "Recurring Payment",
      "Payer": "sandytesting2@gmail.com",
      "PayerDisplayName": "SandboxTest Account",
      "TransactionID": "4FK349568U280804A",
      "Status": "Completed",
      "GrossAmount": {
        "currencyID": "USD",
        "value": "1.00"
      },
      "FeeAmount": {
        "currencyID": "USD",
        "value": "-0.33"
      },
      "NetAmount": {
        "currencyID": "USD",
        "value": "0.67"
      }
    },
    {
      "Timestamp": "2015-12-22T10:07:49+00:00",
      "Timezone": "GMT",
      "Type": "Recurring Payment",
      "Payer": "cruzazul_magistroni@hotmail.com",
      "PayerDisplayName": "Uriel Hernandez",
      "TransactionID": "5DH88203LM510351V",
      "Status": "Completed",
      "GrossAmount": {
        "currencyID": "USD",
        "value": "9.00"
      },
      "FeeAmount": {
        "currencyID": "USD",
        "value": "-0.56"
      },
      "NetAmount": {
        "currencyID": "USD",
        "value": "8.44"
      }
    },
    {
      "Timestamp": "2015-12-22T10:07:45+00:00",
      "Timezone": "GMT",
      "Type": "Recurring Payment",
      "Payer": "skualys-buyer@hotmail.fr",
      "PayerDisplayName": "test buyer",
      "TransactionID": "5LE08737CL588002S",
      "Status": "Completed",
      "GrossAmount": {
        "currencyID": "USD",
        "value": "1.00"
      },
      "FeeAmount": {
        "currencyID": "USD",
        "value": "-0.34"
      },
      "NetAmount": {
        "currencyID": "USD",
        "value": "0.66"
      }
    },
    {
      "Timestamp": "2015-12-22T10:07:41+00:00",
      "Timezone": "GMT",
      "Type": "Recurring Payment",
      "Payer": "skualys-buyer@hotmail.fr",
      "PayerDisplayName": "test buyer",
      "TransactionID": "1WJ83688L4631720V",
      "Status": "Completed",
      "GrossAmount": {
        "currencyID": "USD",
        "value": "1.00"
      },
      "FeeAmount": {
        "currencyID": "USD",
        "value": "-0.34"
      },
      "NetAmount": {
        "currencyID": "USD",
        "value": "0.66"
      }
    },
    {
      "Timestamp": "2015-12-22T10:07:37+00:00",
      "Timezone": "GMT",
      "Type": "Recurring Payment",
      "Payer": "nunoabc92-buyer@gmail.com",
      "PayerDisplayName": "test buyer",
      "TransactionID": "18X16552MD012751J",
      "Status": "Completed",
      "GrossAmount": {
        "currencyID": "USD",
        "value": "1.00"
      },
      "FeeAmount": {
        "currencyID": "USD",
        "value": "-0.33"
      },
      "NetAmount": {
        "currencyID": "USD",
        "value": "0.67"
      }
    },
    {
      "Timestamp": "2015-12-22T10:07:33+00:00",
      "Timezone": "GMT",
      "Type": "Recurring Payment",
      "Payer": "kmckenna@dog.com",
      "PayerDisplayName": "Kathleen Tester",
      "TransactionID": "68G381861C665882B",
      "Status": "Completed",
      "GrossAmount": {
        "currencyID": "USD",
        "value": "1.00"
      },
      "FeeAmount": {
        "currencyID": "USD",
        "value": "-0.33"
      },
      "NetAmount": {
        "currencyID": "USD",
        "value": "0.67"
      }
    },
    {
      "Timestamp": "2015-12-22T10:07:30+00:00",
      "Timezone": "GMT",
      "Type": "Recurring Payment",
      "Payer": "info-buyer@joserubia.com",
      "PayerDisplayName": "test buyer",
      "TransactionID": "2S7812361S5483537",
      "Status": "Completed",
      "GrossAmount": {
        "currencyID": "USD",
        "value": "1.00"
      },
      "FeeAmount": {
        "currencyID": "USD",
        "value": "-0.34"
      },
      "NetAmount": {
        "currencyID": "USD",
        "value": "0.66"
      }
    },
    {
      "Timestamp": "2015-12-22T10:07:27+00:00",
      "Timezone": "GMT",
      "Type": "Recurring Payment",
      "Payer": "yahoosoo80@gmail.com",
      "PayerDisplayName": "Test yaoo soo",
      "TransactionID": "42B35498H4383651L",
      "Status": "Completed",
      "GrossAmount": {
        "currencyID": "USD",
        "value": "1.00"
      },
      "FeeAmount": {
        "currencyID": "USD",
        "value": "-0.33"
      },
      "NetAmount": {
        "currencyID": "USD",
        "value": "0.67"
      }
    },
    {
      "Timestamp": "2015-12-22T10:07:24+00:00",
      "Timezone": "GMT",
      "Type": "Recurring Payment",
      "Payer": "ebay-facilitator@absoft.pl",
      "PayerDisplayName": "test account's Test Store",
      "TransactionID": "4B707159XF058373Y",
      "Status": "Completed",
      "GrossAmount": {
        "currencyID": "USD",
        "value": "1.00"
      },
      "FeeAmount": {
        "currencyID": "USD",
        "value": "-0.33"
      },
      "NetAmount": {
        "currencyID": "USD",
        "value": "0.67"
      }
    },
    {
      "Timestamp": "2015-12-22T10:07:20+00:00",
      "Timezone": "GMT",
      "Type": "Recurring Payment",
      "Payer": "dp_buyer_pp_US_1437685453094872@paypal.com",
      "PayerDisplayName": "First Last",
      "TransactionID": "9J043659SD8553935",
      "Status": "Completed",
      "GrossAmount": {
        "currencyID": "USD",
        "value": "1.00"
      },
      "FeeAmount": {
        "currencyID": "USD",
        "value": "-0.33"
      },
      "NetAmount": {
        "currencyID": "USD",
        "value": "0.67"
      }
    },
    {
      "Timestamp": "2015-12-22T10:07:17+00:00",
      "Timezone": "GMT",
      "Type": "Recurring Payment",
      "Payer": "amostajo-buyer@gmail.com",
      "PayerDisplayName": "test buyer",
      "TransactionID": "1W497627MV003993A",
      "Status": "Completed",
      "GrossAmount": {
        "currencyID": "USD",
        "value": "1.00"
      },
      "FeeAmount": {
        "currencyID": "USD",
        "value": "-0.33"
      },
      "NetAmount": {
        "currencyID": "USD",
        "value": "0.67"
      }
    },
    {
      "Timestamp": "2015-12-22T10:07:14+00:00",
      "Timezone": "GMT",
      "Type": "Recurring Payment",
      "Payer": "ebay-facilitator@absoft.pl",
      "PayerDisplayName": "test account's Test Store",
      "TransactionID": "22D70913CN2047606",
      "Status": "Completed",
      "GrossAmount": {
        "currencyID": "USD",
        "value": "1.00"
      },
      "FeeAmount": {
        "currencyID": "USD",
        "value": "-0.33"
      },
      "NetAmount": {
        "currencyID": "USD",
        "value": "0.67"
      }
    },
    {
      "Timestamp": "2015-12-22T10:07:10+00:00",
      "Timezone": "GMT",
      "Type": "Recurring Payment",
      "Payer": "anil.h@niharinfo.com",
      "PayerDisplayName": "BSN SURYANARAYANA",
      "TransactionID": "1TB29340PW179684L",
      "Status": "Completed",
      "GrossAmount": {
        "currencyID": "USD",
        "value": "1.00"
      },
      "FeeAmount": {
        "currencyID": "USD",
        "value": "-0.33"
      },
      "NetAmount": {
        "currencyID": "USD",
        "value": "0.67"
      }
    },
    {
      "Timestamp": "2015-12-22T10:07:06+00:00",
      "Timezone": "GMT",
      "Type": "Recurring Payment",
      "Payer": "yogesh.dhande_b@iauro.com",
      "PayerDisplayName": "Test Buyer",
      "TransactionID": "68947405LH658941A",
      "Status": "Completed",
      "GrossAmount": {
        "currencyID": "USD",
        "value": "1.00"
      },
      "FeeAmount": {
        "currencyID": "USD",
        "value": "-0.33"
      },
      "NetAmount": {
        "currencyID": "USD",
        "value": "0.67"
      }
    },
    {
      "Timestamp": "2015-12-22T10:07:03+00:00",
      "Timezone": "GMT",
      "Type": "Recurring Payment",
      "Payer": "neel.shah421-buyer-1@gmail.com",
      "PayerDisplayName": "Test Buyer",
      "TransactionID": "5L6355023V2412118",
      "Status": "Completed",
      "GrossAmount": {
        "currencyID": "USD",
        "value": "1.00"
      },
      "FeeAmount": {
        "currencyID": "USD",
        "value": "-0.34"
      },
      "NetAmount": {
        "currencyID": "USD",
        "value": "0.66"
      }
    },
    {
      "Timestamp": "2015-12-22T10:07:00+00:00",
      "Timezone": "GMT",
      "Type": "Recurring Payment",
      "Payer": "kotlik.vladimir.14@gmail.com",
      "PayerDisplayName": "VVV VVV's Test Store",
      "TransactionID": "3LG07202RP554094X",
      "Status": "Completed",
      "GrossAmount": {
        "currencyID": "USD",
        "value": "1.00"
      },
      "FeeAmount": {
        "currencyID": "USD",
        "value": "-0.33"
      },
      "NetAmount": {
        "currencyID": "USD",
        "value": "0.67"
      }
    },
    {
      "Timestamp": "2015-12-22T10:06:56+00:00",
      "Timezone": "GMT",
      "Type": "Recurring Payment",
      "Payer": "client@yoozon.com",
      "PayerDisplayName": "John Doe",
      "TransactionID": "17E0645805409300R",
      "Status": "Completed",
      "GrossAmount": {
        "currencyID": "USD",
        "value": "1.00"
      },
      "FeeAmount": {
        "currencyID": "USD",
        "value": "-0.33"
      },
      "NetAmount": {
        "currencyID": "USD",
        "value": "0.67"
      }
    },
    {
      "Timestamp": "2015-12-22T10:06:52+00:00",
      "Timezone": "GMT",
      "Type": "Recurring Payment",
      "Payer": "eoccy-buyer@yahoo.com",
      "PayerDisplayName": "test buyer",
      "TransactionID": "89U38635PH9852159",
      "Status": "Completed",
      "GrossAmount": {
        "currencyID": "USD",
        "value": "1.00"
      },
      "FeeAmount": {
        "currencyID": "USD",
        "value": "-0.33"
      },
      "NetAmount": {
        "currencyID": "USD",
        "value": "0.67"
      }
    },
    {
      "Timestamp": "2015-12-22T10:06:49+00:00",
      "Timezone": "GMT",
      "Type": "Recurring Payment",
      "Payer": "357307667@qqq.com",
      "PayerDisplayName": "shaoyun zhang",
      "TransactionID": "5Y736058J8070983A",
      "Status": "Completed",
      "GrossAmount": {
        "currencyID": "USD",
        "value": "6.00"
      },
      "FeeAmount": {
        "currencyID": "USD",
        "value": "-0.53"
      },
      "NetAmount": {
        "currencyID": "USD",
        "value": "5.47"
      }
    },
    {
      "Timestamp": "2015-12-22T10:06:46+00:00",
      "Timezone": "GMT",
      "Type": "Recurring Payment",
      "Payer": "357307667@qqq.com",
      "PayerDisplayName": "shaoyun zhang",
      "TransactionID": "8Y35883387403693X",
      "Status": "Completed",
      "GrossAmount": {
        "currencyID": "USD",
        "value": "6.00"
      },
      "FeeAmount": {
        "currencyID": "USD",
        "value": "-0.53"
      },
      "NetAmount": {
        "currencyID": "USD",
        "value": "5.47"
      }
    },
    {
      "Timestamp": "2015-12-22T10:06:42+00:00",
      "Timezone": "GMT",
      "Type": "Recurring Payment",
      "Payer": "delete-3S87HC4VHVBG4_540048@sandbox.paypal.com",
      "PayerDisplayName": "autotextme",
      "TransactionID": "85V570192F775951F",
      "Status": "Completed",
      "GrossAmount": {
        "currencyID": "USD",
        "value": "1.00"
      },
      "FeeAmount": {
        "currencyID": "USD",
        "value": "-0.33"
      },
      "NetAmount": {
        "currencyID": "USD",
        "value": "0.67"
      }
    },
    {
      "Timestamp": "2015-12-22T10:06:39+00:00",
      "Timezone": "GMT",
      "Type": "Recurring Payment",
      "Payer": "wannabeender@yahoo.com",
      "PayerDisplayName": "Testoni Paypalin",
      "TransactionID": "0C6291169R199124C",
      "Status": "Completed",
      "GrossAmount": {
        "currencyID": "USD",
        "value": "1.00"
      },
      "FeeAmount": {
        "currencyID": "USD",
        "value": "-0.33"
      },
      "NetAmount": {
        "currencyID": "USD",
        "value": "0.67"
      }
    },
    {
      "Timestamp": "2015-12-22T10:06:36+00:00",
      "Timezone": "GMT",
      "Type": "Recurring Payment",
      "Payer": "oss8181-buyer@gmail.com",
      "PayerDisplayName": "test buyer",
      "TransactionID": "8FN20234GH419512K",
      "Status": "Completed",
      "GrossAmount": {
        "currencyID": "USD",
        "value": "1.00"
      },
      "FeeAmount": {
        "currencyID": "USD",
        "value": "-0.33"
      },
      "NetAmount": {
        "currencyID": "USD",
        "value": "0.67"
      }
    },
    {
      "Timestamp": "2015-12-22T10:06:32+00:00",
      "Timezone": "GMT",
      "Type": "Recurring Payment",
      "Payer": "iespinosa-buyer@abargon.com",
      "PayerDisplayName": "test buyer",
      "TransactionID": "129413080R112794D",
      "Status": "Completed",
      "GrossAmount": {
        "currencyID": "USD",
        "value": "1.00"
      },
      "FeeAmount": {
        "currencyID": "USD",
        "value": "-0.34"
      },
      "NetAmount": {
        "currencyID": "USD",
        "value": "0.66"
      }
    },
    {
      "Timestamp": "2015-12-22T10:06:29+00:00",
      "Timezone": "GMT",
      "Type": "Recurring Payment",
      "Payer": "theodorhanu-buyer@gmail.com",
      "PayerDisplayName": "Test Buyer",
      "TransactionID": "4H525807J1673600X",
      "Status": "Completed",
      "GrossAmount": {
        "currencyID": "USD",
        "value": "1.00"
      },
      "FeeAmount": {
        "currencyID": "USD",
        "value": "-0.33"
      },
      "NetAmount": {
        "currencyID": "USD",
        "value": "0.67"
      }
    }
  ]
}
